prdanlz/__init__.py
prdanlz/__main__.py
prdanlz/incident.py
prdanlz/monitor.py
prdanlz/variable.py
prdanlz/libc/__init__.py
prdanlz/libc/libc.py
prdanlz/libc/sysctl.py
prdanlz/libc/tconv.py
prdanlz-0.2.2.dist-info/LICENSE
prdanlz-0.2.2.dist-info/METADATA
prdanlz-0.2.2.dist-info/WHEEL
prdanlz-0.2.2.dist-info/entry_points.txt
prdanlz-0.2.2.dist-info/top_level.txt
prdanlz-0.2.2.dist-info/RECORD
